{
  "generated_at_utc": "2026-05-07T16:54:11.962610+00:00",
  "date": "2026-05-07",
  "timezone": "Asia/Jakarta",
  "window_utc": {
    "start": "2026-05-06T17:00:00+00:00",
    "end": "2026-05-07T17:00:00+00:00"
  },
  "sources": {
    "signals": "/home/kemal/futures/data/Live/super_structure_signals.json",
    "executions": "/home/kemal/futures/data/Live/super_structure_executions.jsonl",
    "ui_theoretical": "/home/kemal/futures/ui/data/trade_events_super_structure_5m.json"
  },
  "summary": {
    "signals": 6,
    "executions": 8,
    "ui_theoretical_trades": 4,
    "critical": 2
  },
  "signal_vs_topstep": [
    {
      "severity": "PASS",
      "signal_id": "sssig_4c16d4a4c7ee61e9",
      "trade_id": "sstrade_f5a29f24949024c9",
      "signal": "BUY",
      "signal_ts": "2026-05-07 01:25",
      "signal_px": 4721.2,
      "execution": "MARKET",
      "exec_ts": "2026-05-07 01:25",
      "exec_px": 4720.0,
      "slippage": -1.199999999999818,
      "note": ""
    },
    {
      "severity": "PASS",
      "signal_id": "sssig_e8974cfd3c21b522",
      "trade_id": "sstrade_f5a29f24949024c9",
      "signal": "CLOSE",
      "signal_ts": "2026-05-07 04:40",
      "signal_px": 4702.637071495463,
      "execution": "FLATTEN",
      "exec_ts": "2026-05-07 04:40",
      "exec_px": 4702.637071495463,
      "slippage": 0.0,
      "note": ""
    },
    {
      "severity": "PASS",
      "signal_id": "sssig_10fab4077f92cad5",
      "trade_id": "sstrade_b316f642a53ce5ea",
      "signal": "SELL",
      "signal_ts": "2026-05-07 04:40",
      "signal_px": 4701.5,
      "execution": "MARKET",
      "exec_ts": "2026-05-07 04:40",
      "exec_px": 4701.0,
      "slippage": -0.5,
      "note": ""
    },
    {
      "severity": "PASS",
      "signal_id": "sssig_b2ccde62bd155cc8",
      "trade_id": "sstrade_b316f642a53ce5ea",
      "signal": "CLOSE",
      "signal_ts": "2026-05-07 06:25",
      "signal_px": 4717.439830299655,
      "execution": "FLATTEN",
      "exec_ts": "2026-05-07 06:25",
      "exec_px": 4717.439830299655,
      "slippage": 0.0,
      "note": ""
    },
    {
      "severity": "PASS",
      "signal_id": "sssig_ffbda3fc1cea65ce",
      "trade_id": "sstrade_1ab0322176137bb9",
      "signal": "BUY",
      "signal_ts": "2026-05-07 06:35",
      "signal_px": 4726.7,
      "execution": "MARKET",
      "exec_ts": "2026-05-07 06:35",
      "exec_px": 4726.5,
      "slippage": -0.1999999999998181,
      "note": ""
    },
    {
      "severity": "PASS",
      "signal_id": "sssig_805b3b52ccc40fda",
      "trade_id": "sstrade_b30b0aecd1f21f03",
      "signal": "SELL",
      "signal_ts": "2026-05-07 15:55",
      "signal_px": 4742.1,
      "execution": "MARKET",
      "exec_ts": "2026-05-07 15:55",
      "exec_px": 4740.7,
      "slippage": -1.4000000000005457,
      "note": ""
    }
  ],
  "signal_vs_ui_theoretical": [
    {
      "severity": "PASS",
      "trade_id": "sstrade_f5a29f24949024c9",
      "side": "Long",
      "signal_entry": "2026-05-07 01:25",
      "signal_exit": "2026-05-07 04:40",
      "ui_entry": "2026-05-07 01:55",
      "ui_exit": "2026-05-07 04:35",
      "entry_delta_min": -30.0,
      "exit_delta_min": 5.0,
      "entry_px_delta": -4.800000000000182,
      "exit_px_delta": -2.8504537112894468e-05,
      "pnl_delta": 48.00071495462987,
      "note": "UI is theoretical backtest"
    },
    {
      "severity": "PASS",
      "trade_id": "sstrade_b316f642a53ce5ea",
      "side": "Short",
      "signal_entry": "2026-05-07 04:40",
      "signal_exit": "2026-05-07 06:25",
      "ui_entry": "2026-05-07 04:35",
      "ui_exit": "2026-05-07 06:15",
      "entry_delta_min": 5.0,
      "exit_delta_min": 10.0,
      "entry_px_delta": -0.6999999999998181,
      "exit_px_delta": 3.029965500900289e-05,
      "pnl_delta": -6.9983029965511605,
      "note": "UI is theoretical backtest"
    },
    {
      "severity": "PASS",
      "trade_id": "sstrade_1ab0322176137bb9",
      "side": "Long",
      "signal_entry": "2026-05-07 06:35",
      "signal_exit": "",
      "ui_entry": "2026-05-07 06:30",
      "ui_exit": "2026-05-07 09:05",
      "entry_delta_min": 5.0,
      "exit_delta_min": null,
      "entry_px_delta": 0.5,
      "exit_px_delta": null,
      "pnl_delta": null,
      "note": "Live was manually closed; signal archive has no CLOSE"
    },
    {
      "severity": "CRITICAL",
      "trade_id": "sstrade_b30b0aecd1f21f03",
      "side": "Short",
      "signal_entry": "2026-05-07 15:55",
      "signal_exit": "",
      "ui_entry": "MISSING",
      "ui_exit": "",
      "entry_delta_min": null,
      "exit_delta_min": null,
      "entry_px_delta": null,
      "exit_px_delta": null,
      "pnl_delta": null,
      "note": "no UI theoretical trade within 30min"
    }
  ],
  "topstep_vs_ui_theoretical": [
    {
      "severity": "PASS",
      "trade_id": "sstrade_f5a29f24949024c9",
      "side": "Long",
      "actual_entry": "2026-05-07 01:25",
      "actual_exit": "2026-05-07 04:40",
      "ui_entry": "2026-05-07 01:55",
      "ui_exit": "2026-05-07 04:35",
      "entry_delta_min": -30.0,
      "exit_delta_min": 5.0,
      "entry_px_delta": -6.0,
      "exit_px_delta": -2.8504537112894468e-05,
      "pnl_delta": 60.00071495462805,
      "note": "UI is theoretical backtest"
    },
    {
      "severity": "PASS",
      "trade_id": "sstrade_b316f642a53ce5ea",
      "side": "Short",
      "actual_entry": "2026-05-07 04:40",
      "actual_exit": "2026-05-07 06:25",
      "ui_entry": "2026-05-07 04:35",
      "ui_exit": "2026-05-07 06:15",
      "entry_delta_min": 5.0,
      "exit_delta_min": 10.0,
      "entry_px_delta": -1.199999999999818,
      "exit_px_delta": 3.029965500900289e-05,
      "pnl_delta": -11.99830299655116,
      "note": "UI is theoretical backtest"
    },
    {
      "severity": "PASS",
      "trade_id": "sstrade_1ab0322176137bb9",
      "side": "Long",
      "actual_entry": "2026-05-07 06:35",
      "actual_exit": "manual",
      "ui_entry": "2026-05-07 06:30",
      "ui_exit": "2026-05-07 09:05",
      "entry_delta_min": 5.0,
      "exit_delta_min": null,
      "entry_px_delta": 0.3000000000001819,
      "exit_px_delta": null,
      "pnl_delta": null,
      "note": "actual was manually closed; exact close time unavailable in legacy log"
    },
    {
      "severity": "CRITICAL",
      "trade_id": "sstrade_b30b0aecd1f21f03",
      "side": "Short",
      "actual_entry": "2026-05-07 15:55",
      "actual_exit": "2026-05-07 16:23",
      "ui_entry": "MISSING",
      "ui_exit": "",
      "entry_delta_min": null,
      "exit_delta_min": null,
      "entry_px_delta": null,
      "exit_px_delta": null,
      "pnl_delta": null,
      "note": "actual execution without matching UI theoretical trade"
    }
  ]
}